commit_check/__init__.py
commit_check/config.py
commit_check/engine.py
commit_check/imperatives.py
commit_check/main.py
commit_check/rule_builder.py
commit_check/rules_catalog.py
commit_check/util.py
commit_check-2.3.0.dist-info/licenses/LICENSE
commit_check-2.3.0.dist-info/METADATA
commit_check-2.3.0.dist-info/WHEEL
commit_check-2.3.0.dist-info/entry_points.txt
commit_check-2.3.0.dist-info/top_level.txt
commit_check-2.3.0.dist-info/RECORD
