Metadata-Version: 2.4
Name: commit-check
Version: 2.3.0
Summary: Check commit message formatting, branch naming, commit author, email, and more.
Author-email: Xianpeng Shen <xianpeng.shen@gmail.com>
License-Expression: MIT
Project-URL: source, https://github.com/commit-check/commit-check
Project-URL: tracker, https://github.com/commit-check/commit-check/issues
Keywords: commit conventions,conventional commits,conventional branch,branch naming,commit-check,message,lint message,devops
Classifier: Development Status :: 5 - Production/Stable
Classifier: Intended Audience :: Developers
Classifier: Natural Language :: English
Classifier: Operating System :: OS Independent
Classifier: Programming Language :: Python :: 3.9
Classifier: Programming Language :: Python :: 3.10
Classifier: Programming Language :: Python :: 3.11
Classifier: Programming Language :: Python :: 3.12
Classifier: Programming Language :: Python :: 3.13
Classifier: Programming Language :: Python :: 3.14
Classifier: Topic :: Utilities
Classifier: Topic :: Software Development :: Build Tools
Classifier: Topic :: Software Development :: Libraries :: Python Modules
Requires-Python: >=3.9
License-File: LICENSE
Requires-Dist: pyyaml
Requires-Dist: tomli>=1.1.0; python_version < "3.11"
Provides-Extra: dev
Requires-Dist: nox; extra == "dev"
Provides-Extra: test
Requires-Dist: coverage; extra == "test"
Requires-Dist: pytest; extra == "test"
Requires-Dist: pytest-mock; extra == "test"
Requires-Dist: pytest-codspeed; extra == "test"
Provides-Extra: docs
Requires-Dist: sphinx<9; extra == "docs"
Requires-Dist: sphinx-immaterial; extra == "docs"
Requires-Dist: sphinx-autobuild; extra == "docs"
Requires-Dist: sphinx_issues; extra == "docs"
Dynamic: license-file
